{
  "@context": [
    "https://linkedsoftwaredependencies.org/bundles/npm/@comunica/runner/^2.0.0/components/context.jsonld",

    "https://linkedsoftwaredependencies.org/bundles/npm/@comunica/actor-rdf-resolve-quad-pattern-hypermedia/^2.0.0/components/context.jsonld"
  ],
  "@id": "urn:comunica:default:Runner",
  "@type": "Runner",
  "actors": [
    {
      "@id": "urn:comunica:default:rdf-resolve-quad-pattern/actors#hypermedia",
      "@type": "ActorRdfResolveQuadPatternHypermedia",
      "mediatorDereferenceRdf": { "@id": "urn:comunica:default:dereference-rdf/mediators#main" },
      "mediatorMetadata": { "@id": "urn:comunica:default:rdf-metadata/mediators#main" },
      "mediatorMetadataExtract": { "@id": "urn:comunica:default:rdf-metadata-extract/mediators#main" },
      "mediatorMetadataAccumulate": { "@id": "urn:comunica:default:rdf-metadata-accumulate/mediators#main" },
      "mediatorRdfResolveHypermedia": { "@id": "urn:comunica:default:rdf-resolve-hypermedia/mediators#main" },
      "mediatorRdfResolveHypermediaLinks": { "@id": "urn:comunica:default:rdf-resolve-hypermedia-links/mediators#main" },
      "mediatorRdfResolveHypermediaLinksQueue": { "@id": "urn:comunica:default:rdf-resolve-hypermedia-links-queue/mediators#main" }
    }
  ]
}
